{"stats":{"minecraft:mined":{"biomesoplenty:cypress_leaves":1},"minecraft:crafted":{"minecraft:oak_planks":20,"minecraft:crafting_table":2,"minecraft:spruce_planks":60},"minecraft:used":{"minecraft:crafting_table":1},"minecraft:picked_up":{"minecraft:iron_chestplate":1,"biomesoplenty:cypress_sapling":1,"minecraft:oak_log":5,"mmorpg:weapon/staff/wood":3,"minecraft:spruce_log":15,"minecraft:oak_sapling":1},"minecraft:custom":{"minecraft:time_since_rest":17698,"minecraft:blood":0,"minecraft:crouch_one_cm":2,"minecraft:magic_shield":0,"minecraft:play_time":17698,"minecraft:sprint_one_cm":6996,"minecraft:walk_one_cm":10688,"minecraft:damage_taken":243,"minecraft:damage_absorbed":531,"minecraft:sneak_time":12,"minecraft:jump":77,"minecraft:energy":50,"minecraft:leave_game":1,"minecraft:health":70,"minecraft:time_since_death":17698,"minecraft:total_world_time":17698,"minecraft:mana":50,"minecraft:fall_one_cm":2855,"minecraft:fly_one_cm":17268}},"DataVersion":3465}